pyproject.toml
siml/__init__.py
siml/__main__/__init__.py
siml/__main__/convert_interim_data.py
siml/__main__/convert_raw_data.py
siml/__main__/optimize.py
siml/__main__/plot_losses.py
siml/__main__/prepare_preprocess_converters.py
siml/__main__/preprocess_interim_data.py
siml/__main__/train.py
siml/__main__/visualize_graph.py
siml/base/siml_const.py
siml/base/siml_enums.py
siml/base/siml_typing.py
siml/config.py
siml/data_parallel.py
siml/datasets.py
siml/inferer.py
siml/loss_operations/__init__.py
siml/loss_operations/loss_assignment.py
siml/loss_operations/loss_calculator.py
siml/loss_operations/loss_calculator_builder.py
siml/loss_operations/loss_selector.py
siml/mains.py
siml/networks/__init__.py
siml/networks/abstract_equivariant_gnn.py
siml/networks/abstract_gcn.py
siml/networks/activation.py
siml/networks/activations.py
siml/networks/array2diagmat.py
siml/networks/array2symmat.py
siml/networks/boundary.py
siml/networks/concatenator.py
siml/networks/deepsets.py
siml/networks/einops.py
siml/networks/einsum.py
siml/networks/gcn.py
siml/networks/group.py
siml/networks/id_mlp.py
siml/networks/identity.py
siml/networks/integration.py
siml/networks/iso_gcn.py
siml/networks/lstm.py
siml/networks/message_passing.py
siml/networks/mlp.py
siml/networks/nan_mlp.py
siml/networks/network.py
siml/networks/normalized_mlp.py
siml/networks/penn.py
siml/networks/pinv_mlp.py
siml/networks/projection.py
siml/networks/proportional.py
siml/networks/pyg/__init__.py
siml/networks/pyg/abstract_pyg_gcn.py
siml/networks/pyg/cluster_gcn.py
siml/networks/pyg/gcnii.py
siml/networks/pyg/gcnii_pytorch_geometric.py
siml/networks/pyg/gin.py
siml/networks/reducer.py
siml/networks/reshape.py
siml/networks/set_transformer.py
siml/networks/share.py
siml/networks/siml_module.py
siml/networks/sparse.py
siml/networks/spmm.py
siml/networks/symmat2array.py
siml/networks/tcn.py
siml/networks/tensor_operations.py
siml/networks/threshold.py
siml/networks/time_norm.py
siml/networks/translator.py
pysiml-0.2.9.dist-info/LICENSE
pysiml-0.2.9.dist-info/METADATA
pysiml-0.2.9.dist-info/WHEEL
pysiml-0.2.9.dist-info/entry_points.txt
pysiml-0.2.9.dist-info/RECORD
